bconfig/__init__.py
bconfig/bconfig.py
bconfig-2.0.0b3.dist-info/METADATA
bconfig-2.0.0b3.dist-info/WHEEL
bconfig-2.0.0b3.dist-info/top_level.txt
bconfig-2.0.0b3.dist-info/RECORD
