Metadata-Version: 2.1
Name: bconfig
Version: 2.0.0b3
Summary: Blueprints for configurations
Home-page: https://github.com/deadbeef-development/bconfig
Author: Deadbeef-Development
Author-email: deadbeef.development@gmail.com
